MANIFEST.in
README.txt
setup.py
Products/__init__.py
Products.FileSystemSite.egg-info/PKG-INFO
Products.FileSystemSite.egg-info/SOURCES.txt
Products.FileSystemSite.egg-info/dependency_links.txt
Products.FileSystemSite.egg-info/namespace_packages.txt
Products.FileSystemSite.egg-info/not-zip-safe
Products.FileSystemSite.egg-info/requires.txt
Products.FileSystemSite.egg-info/top_level.txt
Products/FileSystemSite/DirectoryView.py
Products/FileSystemSite/ExtensionClassUtils.py
Products/FileSystemSite/FSDTMLMethod.py
Products/FileSystemSite/FSExternalMethod.py
Products/FileSystemSite/FSFile.py
Products/FileSystemSite/FSImage.py
Products/FileSystemSite/FSMetadata.py
Products/FileSystemSite/FSObject.py
Products/FileSystemSite/FSPageTemplate.py
Products/FileSystemSite/FSPropertiesObject.py
Products/FileSystemSite/FSPythonScript.py
Products/FileSystemSite/FSZSQLMethod.py
Products/FileSystemSite/HISTORY.txt
Products/FileSystemSite/LICENSE.txt
Products/FileSystemSite/Permissions.py
Products/FileSystemSite/README.txt
Products/FileSystemSite/ReuseUtils.py
Products/FileSystemSite/TrustedFSPythonScript.py
Products/FileSystemSite/TrustedPythonScript.py
Products/FileSystemSite/TrustedPythonScriptMixin.py
Products/FileSystemSite/__init__.py
Products/FileSystemSite/exceptions.py
Products/FileSystemSite/homepage.stx
Products/FileSystemSite/interfaces.py
Products/FileSystemSite/provider.py
Products/FileSystemSite/refresh.txt
Products/FileSystemSite/utils.py
Products/FileSystemSite/version.txt
Products/FileSystemSite/Extensions/SiteExport.py
Products/FileSystemSite/doc/TRUSTED_LICENSE.txt
Products/FileSystemSite/doc/ZPL.txt
Products/FileSystemSite/dtml/addFSDirView.dtml
Products/FileSystemSite/dtml/custdtml.dtml
Products/FileSystemSite/dtml/custfile.dtml
Products/FileSystemSite/dtml/custimage.dtml
Products/FileSystemSite/dtml/custprops.dtml
Products/FileSystemSite/dtml/custpt.dtml
Products/FileSystemSite/dtml/custpy.dtml
Products/FileSystemSite/dtml/custstx.dtml
Products/FileSystemSite/dtml/custzsql.dtml
Products/FileSystemSite/dtml/dirview_properties.dtml
Products/FileSystemSite/images/cookie.gif
Products/FileSystemSite/images/dirview.gif
Products/FileSystemSite/images/fsdtml.gif
Products/FileSystemSite/images/fsfile.gif
Products/FileSystemSite/images/fsimage.gif
Products/FileSystemSite/images/fsprops.gif
