Metadata-Version: 1.1
Name: Products.FileSystemSite
Version: 2.4
Summary: Make available in ZODB file system resources in Zope 2
Home-page: https://github.com/infrae/Products.FileSystemSite
Author: Zope community
Author-email: info@infrae.com
License: ZPL
Keywords: file system site zope2
Platform: UNKNOWN
Classifier: Framework :: Zope2
Classifier: License :: OSI Approved :: Zope Public License
Classifier: Programming Language :: Python
Classifier: Topic :: Software Development :: Libraries :: Python Modules
